{"cameraMode":{"drawMode":0,"name":"Shaded","section":"Shading Mode"},"sceneLighting":true,"audioPlay":false,"sceneViewState":{"m_AlwaysRefresh":false,"showFog":true,"showSkybox":true,"showFlares":true,"showImageEffects":true,"showParticleSystems":true,"showVisualEffectGraphs":true,"m_FxEnabled":true},"in2DMode":false,"pivot":{"x":-0.6425395011901856,"y":-5.180853843688965,"z":8.181880950927735},"rotation":{"x":-0.29723408818244936,"y":0.011169797740876675,"z":-0.003471112111583352,"w":-0.9547548294067383},"size":9.95388126373291,"orthographic":false}